{
    "CustomerKey": "Case_Salesforce",
    "Name": "Case_Salesforce",
    "Description": "",
    "IsSendable": false,
    "IsTestable": false,
    "DataRetentionPeriodUnitOfMeasure": 0,
    "RowBasedRetention": false,
    "ResetRetentionPeriodOnImport": false,
    "DeleteAtEndOfRetentionPeriod": false,
    "RetainUntil": "",
    "Fields": [
        {
            "Name": "AccountId",
            "DefaultValue": "",
            "MaxLength": 18,
            "IsRequired": false,
            "IsPrimaryKey": false,
            "FieldType": "Text"
        },
        {
            "Name": "CaseNumber",
            "DefaultValue": "",
            "MaxLength": 30,
            "IsRequired": false,
            "IsPrimaryKey": false,
            "FieldType": "Text"
        },
        {
            "Name": "ClosedDate",
            "DefaultValue": "",
            "IsRequired": false,
            "IsPrimaryKey": false,
            "FieldType": "Date"
        },
        {
            "Name": "ContactEmail",
            "DefaultValue": "",
            "MaxLength": 80,
            "IsRequired": false,
            "IsPrimaryKey": false,
            "FieldType": "EmailAddress"
        },
        {
            "Name": "ContactId",
            "DefaultValue": "",
            "MaxLength": 18,
            "IsRequired": false,
            "IsPrimaryKey": false,
            "FieldType": "Text"
        },
        {
            "Name": "ContactMobile",
            "DefaultValue": "",
            "MaxLength": 40,
            "IsRequired": false,
            "IsPrimaryKey": false,
            "FieldType": "Phone"
        },
        {
            "Name": "ContactPhone",
            "DefaultValue": "",
            "MaxLength": 40,
            "IsRequired": false,
            "IsPrimaryKey": false,
            "FieldType": "Phone"
        },
        {
            "Name": "CreatedById",
            "DefaultValue": "",
            "MaxLength": 18,
            "IsRequired": false,
            "IsPrimaryKey": false,
            "FieldType": "Text"
        },
        {
            "Name": "CreatedDate",
            "DefaultValue": "",
            "IsRequired": false,
            "IsPrimaryKey": false,
            "FieldType": "Date"
        },
        {
            "Name": "Description",
            "DefaultValue": "",
            "MaxLength": 4000,
            "IsRequired": false,
            "IsPrimaryKey": false,
            "FieldType": "Text"
        },
        {
            "Name": "Id",
            "DefaultValue": "",
            "MaxLength": 18,
            "IsRequired": true,
            "IsPrimaryKey": true,
            "FieldType": "Text"
        },
        {
            "Name": "LastModifiedById",
            "DefaultValue": "",
            "MaxLength": 18,
            "IsRequired": false,
            "IsPrimaryKey": false,
            "FieldType": "Text"
        },
        {
            "Name": "lumen__unCase_Resolved_Date__c",
            "DefaultValue": "",
            "IsRequired": false,
            "IsPrimaryKey": false,
            "FieldType": "Date"
        },
        {
            "Name": "lumen__unEscalated_UserHeirarchy__c",
            "DefaultValue": "",
            "MaxLength": 18,
            "IsRequired": false,
            "IsPrimaryKey": false,
            "FieldType": "Text"
        },
        {
            "Name": "lumen__unProgram__c",
            "DefaultValue": "",
            "MaxLength": 255,
            "IsRequired": false,
            "IsPrimaryKey": false,
            "FieldType": "Text"
        },
        {
            "Name": "lumen__unResolution__c",
            "DefaultValue": "",
            "MaxLength": 4000,
            "IsRequired": false,
            "IsPrimaryKey": false,
            "FieldType": "Text"
        },
        {
            "Name": "lumen__unResolved_Date__c",
            "DefaultValue": "",
            "IsRequired": false,
            "IsPrimaryKey": false,
            "FieldType": "Date"
        },
        {
            "Name": "lumen__unStatus_Change_Date__c",
            "DefaultValue": "",
            "IsRequired": false,
            "IsPrimaryKey": false,
            "FieldType": "Date"
        },
        {
            "Name": "lumen__unSub_Status__c",
            "DefaultValue": "",
            "MaxLength": 255,
            "IsRequired": false,
            "IsPrimaryKey": false,
            "FieldType": "Text"
        },
        {
            "Name": "lumen__unSub_Type__c",
            "DefaultValue": "",
            "MaxLength": 255,
            "IsRequired": false,
            "IsPrimaryKey": false,
            "FieldType": "Text"
        },
        {
            "Name": "MasterRecordId",
            "DefaultValue": "",
            "MaxLength": 18,
            "IsRequired": false,
            "IsPrimaryKey": false,
            "FieldType": "Text"
        },
        {
            "Name": "Origin",
            "DefaultValue": "",
            "MaxLength": 255,
            "IsRequired": false,
            "IsPrimaryKey": false,
            "FieldType": "Text"
        },
        {
            "Name": "OwnerId",
            "DefaultValue": "",
            "MaxLength": 18,
            "IsRequired": false,
            "IsPrimaryKey": false,
            "FieldType": "Text"
        },
        {
            "Name": "ParentId",
            "DefaultValue": "",
            "MaxLength": 18,
            "IsRequired": false,
            "IsPrimaryKey": false,
            "FieldType": "Text"
        },
        {
            "Name": "Reason",
            "DefaultValue": "",
            "MaxLength": 255,
            "IsRequired": false,
            "IsPrimaryKey": false,
            "FieldType": "Text"
        },
        {
            "Name": "RecordTypeId",
            "DefaultValue": "",
            "MaxLength": 18,
            "IsRequired": false,
            "IsPrimaryKey": false,
            "FieldType": "Text"
        },
        {
            "Name": "Status",
            "DefaultValue": "",
            "MaxLength": 255,
            "IsRequired": false,
            "IsPrimaryKey": false,
            "FieldType": "Text"
        },
        {
            "Name": "Subject",
            "DefaultValue": "",
            "MaxLength": 255,
            "IsRequired": false,
            "IsPrimaryKey": false,
            "FieldType": "Text"
        },
        {
            "Name": "Type",
            "DefaultValue": "",
            "MaxLength": 255,
            "IsRequired": false,
            "IsPrimaryKey": false,
            "FieldType": "Text"
        }
    ],
    "r__folder_ContentType": "synchronizeddataextension",
    "r__folder_Path": "Synchronized Data Extensions"
}
